CHANGES.txt
bootstrap.py
buildout.cfg
setup.py
src/ice/__init__.py
src/ice.template.egg-info/PKG-INFO
src/ice.template.egg-info/SOURCES.txt
src/ice.template.egg-info/dependency_links.txt
src/ice.template.egg-info/namespace_packages.txt
src/ice.template.egg-info/not-zip-safe
src/ice.template.egg-info/requires.txt
src/ice.template.egg-info/top_level.txt
src/ice/template/README.txt
src/ice/template/__init__.py
src/ice/template/configure.zcml
src/ice/template/interfaces.py
src/ice/template/meta.zcml
src/ice/template/property.py
src/ice/template/templates.py
src/ice/template/zcml.py
src/ice/template/browser/__init__.py
src/ice/template/browser/configure.zcml
src/ice/template/browser/edit.pt
src/ice/template/browser/edit.py
src/ice/template/browser/publisher.py
src/ice/template/browser/storages.py
src/ice/template/browser/templates.py
src/ice/template/tests/__init__.py
src/ice/template/tests/configure.zcml
src/ice/template/tests/ftesting.zcml
src/ice/template/tests/ftests.py
src/ice/template/tests/ftests.txt
src/ice/template/tests/interfaces.py
src/ice/template/tests/layout.pt
src/ice/template/tests/sampledata.py
src/ice/template/tests/sampledata.zcml
src/ice/template/tests/tests.py
src/ice/template/tests/tmpl/footer.html
src/ice/template/tests/tmpl/registration.tmpl
src/ice/template/tests/tmpl/welcome.tmpl