Metadata-Version: 1.0
Name: ice.template
Version: 0.1.0
Summary: Persistent cheetah templates
Home-page: http://launchpad.net/ice.template
Author: Ilshad Habibullin
Author-email: astoon.net at gmail.com
License: GPL v.3
Platform: UNKNOWN
Classifier: Development Status :: 4 - Beta
Classifier: Environment :: Web Environment
Classifier: Intended Audience :: Developers
Classifier: License :: OSI Approved :: GNU General Public License (GPL)
Classifier: Programming Language :: Python
Classifier: Natural Language :: English
Classifier: Operating System :: OS Independent
Classifier: Topic :: Internet :: WWW/HTTP :: Site Management
Classifier: Framework :: Zope3
